{
    "key": "group_600555890c1b7",
    "title": "[ CONTENT ] - Try Flexter",
    "fields": [
        {
            "key": "field_600555e9909f4",
            "label": "Intro",
            "name": "",
            "type": "tab",
            "instructions": "",
            "required": 0,
            "conditional_logic": 0,
            "wrapper": {
                "width": "",
                "class": "",
                "id": ""
            },
            "placement": "top",
            "endpoint": 0
        },
        {
            "key": "field_60056f3c14797",
            "label": "Text next to clients",
            "name": "try_intro_clients_info",
            "type": "text",
            "instructions": "",
            "required": 0,
            "conditional_logic": 0,
            "wrapper": {
                "width": "",
                "class": "",
                "id": ""
            },
            "default_value": "",
            "placeholder": "",
            "prepend": "",
            "append": "",
            "maxlength": ""
        },
        {
            "key": "field_600555f8909f5",
            "label": "Clients",
            "name": "try_intro_clients",
            "type": "gallery",
            "instructions": "",
            "required": 0,
            "conditional_logic": 0,
            "wrapper": {
                "width": "",
                "class": "",
                "id": ""
            },
            "return_format": "array",
            "preview_size": "medium",
            "insert": "append",
            "library": "all",
            "min": "",
            "max": "",
            "min_width": "",
            "min_height": "",
            "min_size": "",
            "max_width": "",
            "max_height": "",
            "max_size": "",
            "mime_types": ""
        },
        {
            "key": "field_60055605909f6",
            "label": "Heading",
            "name": "try_intro_heading",
            "type": "textarea",
            "instructions": "",
            "required": 0,
            "conditional_logic": 0,
            "wrapper": {
                "width": "",
                "class": "",
                "id": ""
            },
            "default_value": "",
            "placeholder": "",
            "maxlength": "",
            "rows": "",
            "new_lines": "br"
        },
        {
            "key": "field_6005560b909f7",
            "label": "Text",
            "name": "try_intro_text",
            "type": "wysiwyg",
            "instructions": "<strong>NOTE:<\/strong><\/br>\r\n- For first-level subheading use  H3<\/br>\r\n- For second-level subheading use  H4<\/br>\r\n- For third-level subheading use  H5<\/br>\r\n- For line between text click on toolbar toggle and then click <strong>Horizontal line<\/strong><\/br>\r\n- For list use UL (Bulleted list)<\/br>",
            "required": 0,
            "conditional_logic": 0,
            "wrapper": {
                "width": "",
                "class": "",
                "id": ""
            },
            "default_value": "",
            "tabs": "all",
            "toolbar": "full",
            "media_upload": 0,
            "delay": 0
        },
        {
            "key": "field_600561a18c648",
            "label": "What does the free version include",
            "name": "",
            "type": "tab",
            "instructions": "",
            "required": 0,
            "conditional_logic": 0,
            "wrapper": {
                "width": "",
                "class": "",
                "id": ""
            },
            "placement": "top",
            "endpoint": 0
        },
        {
            "key": "field_600562a98c649",
            "label": "Heading",
            "name": "free_heading",
            "type": "text",
            "instructions": "",
            "required": 0,
            "conditional_logic": 0,
            "wrapper": {
                "width": "",
                "class": "",
                "id": ""
            },
            "default_value": "",
            "placeholder": "",
            "prepend": "",
            "append": "",
            "maxlength": ""
        },
        {
            "key": "field_600562bd8c64a",
            "label": "Image",
            "name": "free_image",
            "type": "image",
            "instructions": "",
            "required": 0,
            "conditional_logic": 0,
            "wrapper": {
                "width": "",
                "class": "",
                "id": ""
            },
            "return_format": "url",
            "preview_size": "medium",
            "library": "all",
            "min_width": "",
            "min_height": "",
            "min_size": "",
            "max_width": "",
            "max_height": "",
            "max_size": "",
            "mime_types": ""
        },
        {
            "key": "field_600562d18c64b",
            "label": "List",
            "name": "free_list",
            "type": "wysiwyg",
            "instructions": "<strong>NOTE:<\/strong> Add list of what free version includes as <strong>Bulleted List<\/strong>",
            "required": 0,
            "conditional_logic": 0,
            "wrapper": {
                "width": "",
                "class": "",
                "id": ""
            },
            "default_value": "",
            "tabs": "all",
            "toolbar": "full",
            "media_upload": 0,
            "delay": 0
        },
        {
            "key": "field_6005717ce6348",
            "label": "Steps",
            "name": "",
            "type": "tab",
            "instructions": "",
            "required": 0,
            "conditional_logic": 0,
            "wrapper": {
                "width": "",
                "class": "",
                "id": ""
            },
            "placement": "top",
            "endpoint": 0
        },
        {
            "key": "field_600572795a2bd",
            "label": "Heading",
            "name": "try_steps_heading",
            "type": "text",
            "instructions": "",
            "required": 0,
            "conditional_logic": 0,
            "wrapper": {
                "width": "",
                "class": "",
                "id": ""
            },
            "default_value": "",
            "placeholder": "",
            "prepend": "",
            "append": "",
            "maxlength": ""
        },
        {
            "key": "field_600572b98990b",
            "label": "Top Text",
            "name": "try_steps_top_text",
            "type": "wysiwyg",
            "instructions": "",
            "required": 0,
            "conditional_logic": 0,
            "wrapper": {
                "width": "",
                "class": "",
                "id": ""
            },
            "default_value": "",
            "tabs": "all",
            "toolbar": "full",
            "media_upload": 1,
            "delay": 0
        },
        {
            "key": "field_6005730474636",
            "label": "Steps",
            "name": "try_steps_repeater",
            "type": "repeater",
            "instructions": "",
            "required": 0,
            "conditional_logic": 0,
            "wrapper": {
                "width": "",
                "class": "",
                "id": ""
            },
            "collapsed": "",
            "min": 0,
            "max": 0,
            "layout": "table",
            "button_label": "",
            "sub_fields": [
                {
                    "key": "field_6005730474637",
                    "label": "Step Image",
                    "name": "try_steps_step_image",
                    "type": "image",
                    "instructions": "",
                    "required": 0,
                    "conditional_logic": 0,
                    "wrapper": {
                        "width": "",
                        "class": "",
                        "id": ""
                    },
                    "return_format": "url",
                    "preview_size": "medium",
                    "library": "all",
                    "min_width": "",
                    "min_height": "",
                    "min_size": "",
                    "max_width": "",
                    "max_height": "",
                    "max_size": "",
                    "mime_types": ""
                },
                {
                    "key": "field_6005730474638",
                    "label": "Step Content",
                    "name": "try_steps_step_content",
                    "type": "wysiwyg",
                    "instructions": "<strong>NOTE:<\/strong><\/br>\r\n- For first-level subheading use  H3<\/br>\r\n- For second-level subheading use  H4<\/br>\r\n- For line between text click on toolbar toggle and then click <strong>Horizontal line<\/strong><\/br>\r\n- For list use UL (Bulleted list)<\/br>",
                    "required": 0,
                    "conditional_logic": 0,
                    "wrapper": {
                        "width": "",
                        "class": "",
                        "id": ""
                    },
                    "default_value": "",
                    "tabs": "all",
                    "toolbar": "full",
                    "media_upload": 0,
                    "delay": 0
                }
            ]
        },
        {
            "key": "field_6005733550074",
            "label": "Bottom Text",
            "name": "try_steps_bottom_text",
            "type": "wysiwyg",
            "instructions": "<strong>NOTE:<\/strong><\/br>\r\n- For first-level subheading use  H3<\/br>\r\n- For second-level subheading use  H4<\/br>\r\n- For third-level subheading use  H5<\/br>\r\n- For line between text click on toolbar toggle and then click <strong>Horizontal line<\/strong><\/br>\r\n- For list use UL (Bulleted list)<\/br>",
            "required": 0,
            "conditional_logic": 0,
            "wrapper": {
                "width": "",
                "class": "",
                "id": ""
            },
            "default_value": "",
            "tabs": "all",
            "toolbar": "full",
            "media_upload": 0,
            "delay": 0
        },
        {
            "key": "field_600566ac6538e",
            "label": "Quote",
            "name": "",
            "type": "tab",
            "instructions": "",
            "required": 0,
            "conditional_logic": 0,
            "wrapper": {
                "width": "",
                "class": "",
                "id": ""
            },
            "placement": "top",
            "endpoint": 0
        },
        {
            "key": "field_6005671f6538f",
            "label": "Quote",
            "name": "try_quote",
            "type": "wysiwyg",
            "instructions": "",
            "required": 0,
            "conditional_logic": 0,
            "wrapper": {
                "width": "",
                "class": "",
                "id": ""
            },
            "default_value": "",
            "tabs": "all",
            "toolbar": "full",
            "media_upload": 0,
            "delay": 0
        },
        {
            "key": "field_6005674565390",
            "label": "Quote Author",
            "name": "try_quote_author",
            "type": "text",
            "instructions": "",
            "required": 0,
            "conditional_logic": 0,
            "wrapper": {
                "width": "",
                "class": "",
                "id": ""
            },
            "default_value": "",
            "placeholder": "",
            "prepend": "",
            "append": "",
            "maxlength": ""
        },
        {
            "key": "field_6005679f65391",
            "label": "Who’s it for",
            "name": "",
            "type": "tab",
            "instructions": "",
            "required": 0,
            "conditional_logic": 0,
            "wrapper": {
                "width": "",
                "class": "",
                "id": ""
            },
            "placement": "top",
            "endpoint": 0
        },
        {
            "key": "field_600567cf65392",
            "label": "Heading",
            "name": "try_for_heading",
            "type": "text",
            "instructions": "",
            "required": 0,
            "conditional_logic": 0,
            "wrapper": {
                "width": "",
                "class": "",
                "id": ""
            },
            "default_value": "",
            "placeholder": "",
            "prepend": "",
            "append": "",
            "maxlength": ""
        },
        {
            "key": "field_60056abd65393",
            "label": "Top text",
            "name": "try_for_top_text",
            "type": "wysiwyg",
            "instructions": "",
            "required": 0,
            "conditional_logic": 0,
            "wrapper": {
                "width": "",
                "class": "",
                "id": ""
            },
            "default_value": "",
            "tabs": "all",
            "toolbar": "full",
            "media_upload": 0,
            "delay": 0
        },
        {
            "key": "field_60056adb65394",
            "label": "Image",
            "name": "try_for_image",
            "type": "image",
            "instructions": "",
            "required": 0,
            "conditional_logic": 0,
            "wrapper": {
                "width": "",
                "class": "",
                "id": ""
            },
            "return_format": "url",
            "preview_size": "medium",
            "library": "all",
            "min_width": "",
            "min_height": "",
            "min_size": "",
            "max_width": "",
            "max_height": "",
            "max_size": "",
            "mime_types": ""
        },
        {
            "key": "field_60056aeb65395",
            "label": "List",
            "name": "try_for_list",
            "type": "wysiwyg",
            "instructions": "<strong>NOTE:<\/strong> Use <strong>Bulleted List<\/strong>",
            "required": 0,
            "conditional_logic": 0,
            "wrapper": {
                "width": "",
                "class": "",
                "id": ""
            },
            "default_value": "",
            "tabs": "all",
            "toolbar": "full",
            "media_upload": 0,
            "delay": 0
        },
        {
            "key": "field_60056b3165396",
            "label": "Bottom text",
            "name": "try_for_bottom_text",
            "type": "wysiwyg",
            "instructions": "<strong>NOTE:<\/strong><\/br>\r\n- For first-level subheading use  H3<\/br>\r\n- For second-level subheading use  H4<\/br>\r\n- For third-level subheading use  H5<\/br>\r\n- For line between text click on toolbar toggle and then click <strong>Horizontal line<\/strong><\/br>\r\n- For list use UL (Bulleted list)<\/br>",
            "required": 0,
            "conditional_logic": 0,
            "wrapper": {
                "width": "",
                "class": "",
                "id": ""
            },
            "default_value": "",
            "tabs": "all",
            "toolbar": "full",
            "media_upload": 0,
            "delay": 0
        },
        {
            "key": "field_600557e577e28",
            "label": "Solve Issues",
            "name": "",
            "type": "tab",
            "instructions": "",
            "required": 0,
            "conditional_logic": 0,
            "wrapper": {
                "width": "",
                "class": "",
                "id": ""
            },
            "placement": "top",
            "endpoint": 0
        },
        {
            "key": "field_600557e877e29",
            "label": "Heading",
            "name": "try_solve_heading",
            "type": "text",
            "instructions": "",
            "required": 0,
            "conditional_logic": 0,
            "wrapper": {
                "width": "",
                "class": "",
                "id": ""
            },
            "default_value": "",
            "placeholder": "",
            "prepend": "",
            "append": "",
            "maxlength": ""
        },
        {
            "key": "field_600557ef77e2a",
            "label": "Issues",
            "name": "try_solve_issues",
            "type": "repeater",
            "instructions": "",
            "required": 0,
            "conditional_logic": 0,
            "wrapper": {
                "width": "",
                "class": "",
                "id": ""
            },
            "collapsed": "",
            "min": 0,
            "max": 0,
            "layout": "table",
            "button_label": "",
            "sub_fields": [
                {
                    "key": "field_600557ef77e2b",
                    "label": "Issue Image",
                    "name": "try_solve_issue_image",
                    "type": "image",
                    "instructions": "",
                    "required": 0,
                    "conditional_logic": 0,
                    "wrapper": {
                        "width": "",
                        "class": "",
                        "id": ""
                    },
                    "return_format": "url",
                    "preview_size": "medium",
                    "library": "all",
                    "min_width": "",
                    "min_height": "",
                    "min_size": "",
                    "max_width": "",
                    "max_height": "",
                    "max_size": "",
                    "mime_types": ""
                },
                {
                    "key": "field_600557ef77e2c",
                    "label": "Issue Text",
                    "name": "try_solve_issue_content",
                    "type": "wysiwyg",
                    "instructions": "<strong>NOTE:<\/strong><\/br>\r\n- For first-level subheading use  H3<\/br>\r\n- For second-level subheading use  H4<\/br>\r\n- For third-level subheading use  H5<\/br>\r\n- For blue highlighted heading use H6<\/br>\r\n- For line between text click on toolbar toggle and then click <strong>Horizontal line<\/strong><\/br>\r\n- For list use UL (Unordered list)<\/br>",
                    "required": 0,
                    "conditional_logic": 0,
                    "wrapper": {
                        "width": "",
                        "class": "",
                        "id": ""
                    },
                    "default_value": "",
                    "tabs": "all",
                    "toolbar": "full",
                    "media_upload": 0,
                    "delay": 0
                }
            ]
        },
        {
            "key": "field_60056bb265397",
            "label": "Who are we",
            "name": "",
            "type": "tab",
            "instructions": "",
            "required": 0,
            "conditional_logic": 0,
            "wrapper": {
                "width": "",
                "class": "",
                "id": ""
            },
            "placement": "top",
            "endpoint": 0
        },
        {
            "key": "field_60056bbb65398",
            "label": "Heading",
            "name": "try_who_heading",
            "type": "text",
            "instructions": "",
            "required": 0,
            "conditional_logic": 0,
            "wrapper": {
                "width": "",
                "class": "",
                "id": ""
            },
            "default_value": "",
            "placeholder": "",
            "prepend": "",
            "append": "",
            "maxlength": ""
        },
        {
            "key": "field_60056be465399",
            "label": "Subheading",
            "name": "try_who_subheading",
            "type": "text",
            "instructions": "",
            "required": 0,
            "conditional_logic": 0,
            "wrapper": {
                "width": "",
                "class": "",
                "id": ""
            },
            "default_value": "",
            "placeholder": "",
            "prepend": "",
            "append": "",
            "maxlength": ""
        },
        {
            "key": "field_60056bf36539a",
            "label": "Text",
            "name": "try_who_text",
            "type": "wysiwyg",
            "instructions": "",
            "required": 0,
            "conditional_logic": 0,
            "wrapper": {
                "width": "",
                "class": "",
                "id": ""
            },
            "default_value": "",
            "tabs": "all",
            "toolbar": "full",
            "media_upload": 0,
            "delay": 0
        },
        {
            "key": "field_60056c086539b",
            "label": "What happens after you sign up?",
            "name": "",
            "type": "tab",
            "instructions": "",
            "required": 0,
            "conditional_logic": 0,
            "wrapper": {
                "width": "",
                "class": "",
                "id": ""
            },
            "placement": "top",
            "endpoint": 0
        },
        {
            "key": "field_60056c106539c",
            "label": "Heading",
            "name": "try_what_heading",
            "type": "text",
            "instructions": "",
            "required": 0,
            "conditional_logic": 0,
            "wrapper": {
                "width": "",
                "class": "",
                "id": ""
            },
            "default_value": "",
            "placeholder": "",
            "prepend": "",
            "append": "",
            "maxlength": ""
        },
        {
            "key": "field_60056c346539d",
            "label": "Text",
            "name": "try_what_text",
            "type": "wysiwyg",
            "instructions": "<strong>NOTE:<\/strong><\/br>\r\n- For first-level subheading use  H3<\/br>\r\n- For second-level subheading use  H4<\/br>\r\n- For third-level subheading use  H5<\/br>\r\n- For line between text click on toolbar toggle and then click <strong>Horizontal line<\/strong><\/br>\r\n- For list use UL (Bulleted list)<\/br>\r\n- For <strong>Numbered<\/strong> list use OL (Nubered List)<\/br>",
            "required": 0,
            "conditional_logic": 0,
            "wrapper": {
                "width": "",
                "class": "",
                "id": ""
            },
            "default_value": "",
            "tabs": "all",
            "toolbar": "full",
            "media_upload": 0,
            "delay": 0
        }
    ],
    "location": [
        [
            {
                "param": "page_template",
                "operator": "==",
                "value": "custom-flexter.php"
            }
        ]
    ],
    "menu_order": 0,
    "position": "normal",
    "style": "default",
    "label_placement": "top",
    "instruction_placement": "label",
    "hide_on_screen": "",
    "active": 1,
    "description": "",
    "modified": 1611968239
}